elmax/__init__.py
elmax/constants.py
elmax/exceptions.py
elmax-0.1.3.dist-info/entry_points.txt
elmax-0.1.3.dist-info/LICENSE
elmax-0.1.3.dist-info/WHEEL
elmax-0.1.3.dist-info/METADATA
elmax-0.1.3.dist-info/RECORD
