Metadata-Version: 2.1
Name: elmax
Version: 0.1.3
Summary: Python client for the Elmax Cloud services
Home-page: https://github.com/home-assistant-ecosystem/python-elmax
License: Apache-2.0
Keywords: iot,cloud,home-assistant
Author: Fabian Affolter
Author-email: fabian@affolter-engineering.ch
Requires-Python: >=3.7.0,<4.0.0
Classifier: Development Status :: 3 - Alpha
Classifier: Environment :: Console
Classifier: License :: OSI Approved :: Apache Software License
Classifier: Programming Language :: Python :: 3
Classifier: Programming Language :: Python :: 3.10
Classifier: Programming Language :: Python :: 3.7
Classifier: Programming Language :: Python :: 3.8
Classifier: Programming Language :: Python :: 3.9
Classifier: Topic :: Home Automation
Requires-Dist: httpx (>=0.19,<0.20)
Requires-Dist: yarl (>=1.6,<2.0)
Project-URL: Documentation, https://github.com/home-assistant-ecosystem/python-elmax
Project-URL: Repository, https://github.com/home-assistant-ecosystem/python-elmax
